kt_toposis/__init__.py
kt_toposis/toposis.py
kt_toposis/topsis.py
kt_toposis/trial.py
kt_toposis-1.0.9.dist-info/LICENSE
kt_toposis-1.0.9.dist-info/METADATA
kt_toposis-1.0.9.dist-info/WHEEL
kt_toposis-1.0.9.dist-info/entry_points.txt
kt_toposis-1.0.9.dist-info/top_level.txt
kt_toposis-1.0.9.dist-info/RECORD
